osem/__init__.py
osem/Storage/__init__.py
osem/Storage/HotWaterTank/__init__.py
osem/Storage/HotWaterTank/hot_water_tank.py
osem/Storage/thermal_storage/Layer.py
osem/Storage/thermal_storage/Storage.py
osem/Storage/thermal_storage/StratifiedDynamic.py
osem/Storage/thermal_storage/System.py
osem/Storage/thermal_storage/__init__.py
osem/Storage/thermal_storage/testStratifiedDynamic.py
osem/access_data/__init__.py
osem/access_data/kbob.py
osem/access_data/kpi.py
osem/access_data/meteo.py
osem/access_data/political_objective.py
osem/access_data/price.py
osem/building_demand/__init__.py
osem/building_demand/heat_power_supply_temp.py
osem/building_demand/maximum_legal_heating_demand.py
osem/building_demand/specific_energy_requirements.py
osem/building_demand/static_heating_cooling_Power.py
osem/distribution_network/__init__.py
osem/distribution_network/heat_network.py
osem/energy_conversion/__init__.py
osem/energy_conversion/boiler/__init__.py
osem/energy_conversion/boiler/boiler_behaviour.py
osem/energy_conversion/heat_exchanger/__init__.py
osem/energy_conversion/heat_exchanger/heat_Exchanger.py
osem/energy_conversion/heat_pump/__init__.py
osem/energy_conversion/heat_pump/heat_pump.py
osem/energy_conversion/solar_pv/__init__.py
osem/energy_conversion/solar_pv/solar_pv.py
osem/energy_conversion/solar_thermal/__init__.py
osem/energy_conversion/solar_thermal/solar_thermal.py
osem/energy_conversion/solar_thermal/solar_thermal_production_from_radiation.py
osem/general/__init__.py
osem/general/conf.py
osem/general/helper.py
osem/general/data/__init__.py
osem/general/data/kpi_efficiency_heating.csv
osem/general/data/kpi_example_2.xlsx
osem/general/data/kpi_example_c02.xlsx
osem/general/data/pandangas_info_solver_option.json
osem/general/data/political_obj.csv
osem/general/data/price_create_database.py
osem/general/data/price_database.db
osem/general/data/data_kbob/Liste Oekobilanzdaten im Baubereich 2009-1-2016-gerundet-kWh.xlsx
osem/general/data/data_kbob/__init__.py
osem-0.0.8.dist-info/LICENSE
osem-0.0.8.dist-info/METADATA
osem-0.0.8.dist-info/WHEEL
osem-0.0.8.dist-info/top_level.txt
osem-0.0.8.dist-info/RECORD
