Metadata-Version: 2.1
Name: osem
Version: 0.0.8
Summary: Open Source Energy Features: dedicated tools and methods for energy related models and applications
Home-page: https://www.crem.ch/
Author: CREM
Author-email: osem@crem.ch
License: UNKNOWN
Platform: UNKNOWN
Classifier: Natural Language :: English
Classifier: Programming Language :: Python :: 3.6
Requires-Dist: pandas
Requires-Dist: scipy
Requires-Dist: thermo
Requires-Dist: networkx
Requires-Dist: numpy
Requires-Dist: xlrd
Requires-Dist: fluid
Requires-Dist: mpmath
Requires-Dist: sympy
